{"host":"ip-172-31-47-200.ec2.internal","time":"2026-01-22T00:08:24.584728526+00:00","configuration_version":1769040504,"transaction_uuid":"1f7a29e3-8912-4b26-b4f1-7e8b7d5ea8b6","report_format":12,"puppet_version":"8.1.0","status":"unchanged","transaction_completed":true,"noop":false,"noop_pending":true,"environment":"production","metrics":{"resources":{"name":"resources","label":"Resources","values":[["total","Total",10],["skipped","Skipped",0],["failed","Failed",0],["failed_to_restart","Failed to restart",0],["restarted","Restarted",0],["changed","Changed",0],["out_of_sync","Out of sync",1],["scheduled","Scheduled",0],["corrective_change","Corrective change",0]]},"time":{"name":"time","label":"Time","values":[["package","Package",0.021601159],["user","User",6.27001E-4],["schedule","Schedule",2.53437E-4],["filebucket","Filebucket",4.8788E-5],["config_retrieval","Config retrieval",0.166758782],["transaction_evaluation","Transaction evaluation",0.11097032899999704],["catalog_application","Catalog application",0.13735610199998405],["total","Total",0.150658234]]},"changes":{"name":"changes","label":"Changes","values":[["total","Total",0]]},"events":{"name":"events","label":"Events","values":[["total","Total",1],["failure","Failure",0],["success","Success",0],["noop","Noop",1]]}},"resource_statuses":{"Package[jdk]":{"title":"jdk","file":"/var/aws/emr/bigtop-deploy/puppet/manifests/site.pp","line":80,"resource":"Package[jdk]","resource_type":"Package","provider_used":"dnf","containment_path":["Stage[main]","Main","Package[jdk]"],"evaluation_time":0.021413885,"tags":["package","jdk","class"],"time":"2026-01-22T00:08:24.693896078+00:00","failed":false,"failed_to_restart":false,"changed":false,"out_of_sync":true,"skipped":false,"change_count":0,"out_of_sync_count":1,"events":[{"audited":false,"property":"ensure","previous_value":"purged","desired_value":"present","historical_value":null,"message":"current_value 'purged', should be 'present' (noop)","name":"package_installed","status":"noop","time":"2026-01-22T00:08:24.713785091+00:00","redacted":null,"corrective_change":false}],"corrective_change":false}},"corrective_change":false,"catalog_uuid":"e3ccfa2e-5e79-4a44-87ae-d222fabb21ef","cached_catalog_status":"not_used"}