{"host":"ip-172-31-43-134.ec2.internal","time":"2026-01-18T17:55:15.648582338+00:00","configuration_version":1768758915,"transaction_uuid":"3450c2f7-dbbe-4e80-8e71-54d9ff4eb83a","report_format":12,"puppet_version":"8.1.0","status":"unchanged","transaction_completed":true,"noop":false,"noop_pending":true,"environment":"production","metrics":{"resources":{"name":"resources","label":"Resources","values":[["total","Total",10],["skipped","Skipped",0],["failed","Failed",0],["failed_to_restart","Failed to restart",0],["restarted","Restarted",0],["changed","Changed",0],["out_of_sync","Out of sync",1],["scheduled","Scheduled",0],["corrective_change","Corrective change",0]]},"time":{"name":"time","label":"Time","values":[["package","Package",0.02108274],["user","User",4.29658E-4],["schedule","Schedule",2.45735E-4],["filebucket","Filebucket",1.02739E-4],["config_retrieval","Config retrieval",0.211127269],["transaction_evaluation","Transaction evaluation",0.11268383299997708],["catalog_application","Catalog application",0.15423593200000596],["total","Total",0.180800886]]},"changes":{"name":"changes","label":"Changes","values":[["total","Total",0]]},"events":{"name":"events","label":"Events","values":[["total","Total",1],["failure","Failure",0],["success","Success",0],["noop","Noop",1]]}},"resource_statuses":{"Package[jdk]":{"title":"jdk","file":"/var/aws/emr/bigtop-deploy/puppet/manifests/site.pp","line":80,"resource":"Package[jdk]","resource_type":"Package","provider_used":"dnf","containment_path":["Stage[main]","Main","Package[jdk]"],"evaluation_time":0.020943184,"tags":["package","jdk","class"],"time":"2026-01-18T17:55:15.789854936+00:00","failed":false,"failed_to_restart":false,"changed":false,"out_of_sync":true,"skipped":false,"change_count":0,"out_of_sync_count":1,"events":[{"audited":false,"property":"ensure","previous_value":"purged","desired_value":"present","historical_value":null,"message":"current_value 'purged', should be 'present' (noop)","name":"package_installed","status":"noop","time":"2026-01-18T17:55:15.809374475+00:00","redacted":null,"corrective_change":false}],"corrective_change":false}},"corrective_change":false,"catalog_uuid":"c762127f-ed4c-4127-bab5-ed42cb0b62cd","cached_catalog_status":"not_used"}